keeptalking.py
keeptalking-0.3.3.dist-info/METADATA
keeptalking-0.3.3.dist-info/WHEEL
keeptalking-0.3.3.dist-info/RECORD
