Metadata-Version: 2.3
Name: keeptalking
Version: 0.3.3
Summary: LLM client library OpenAI should have made
License: MIT
Author: Vadim Liventsev
Author-email: dev@vadim.me
Requires-Python: >=3.12,<4.0
Classifier: License :: OSI Approved :: MIT License
Classifier: Programming Language :: Python :: 3
Classifier: Programming Language :: Python :: 3.12
Classifier: Programming Language :: Python :: 3.13
Requires-Dist: openai (>=1.101,<2.0)
Requires-Dist: pydantic (>=2.11,<3.0)
Requires-Dist: tenacity (>=9.1,<10.0)
